{
    "modelName": "New Model",
    "collections": [
        {
            "collectionName": "New 33",
            "type": "object",
            "properties": [
                {
                    "name": "New Field",
                    "hackoladeMeta": {},
                    "isActivated": true,
                    "type": "string",
                    "GUID": "af140ea0-a7b1-11ec-b8be-0f7e6033a1b6",
                    "error": {
                        "name": false,
                        "code": false
                    }
                }
            ],
            "definitions": {
                "type": "definitions",
                "properties": [],
                "GUID": "9f1f95a0-a7b1-11ec-b8be-0f7e6033a1b6"
            },
            "isActivated": true,
            "additionalProperties": false,
            "validationLevel": "Off",
            "validationAction": "Warn",
            "storageEngineName": "WiredTiger",
            "collectionUsers": [],
            "indexes": [],
            "collation": {},
            "sharding": {
                "unique": true,
                "collation": "null"
            },
            "GUID": "9f1d99d0-a7b1-11ec-b8be-0f7e6033a1b6",
            "bucketId": "2855a8a0-a799-11ec-9997-157f1432aaf9"
        }
    ],
    "buckets": [
        {
            "name": "New_Database",
            "type": "bucket",
            "collectionIds": [
                "9f1d99d0-a7b1-11ec-b8be-0f7e6033a1b6"
            ],
            "backgroundColor": {
                "r": 216,
                "g": 0,
                "b": 115,
                "a": 1
            },
            "show": true,
            "isActivated": true,
            "GUID": "2855a8a0-a799-11ec-9997-157f1432aaf9"
        }
    ],
    "views": [],
    "relationships": [],
    "users": [],
    "diagramViews": [],
    "idToNameHashTable": {
        "2855a8a0-a799-11ec-9997-157f1432aaf9": "New_Database",
        "9f1d99d0-a7b1-11ec-b8be-0f7e6033a1b6": "New Collection",
        "af140ea0-a7b1-11ec-b8be-0f7e6033a1b6": "New Field"
    },
    "definitions": {
        "type": "definitions",
        "properties": [],
        "GUID": "26ea7fe1-a799-11ec-9997-157f1432aaf9"
    },
    "polyglotDefinitions": {
        "type": "polyglotDefinitions",
        "properties": [],
        "GUID": "26ea7fe3-a799-11ec-9997-157f1432aaf9"
    },
    "externalDefinitions": {
        "type": "externalDefinitions",
        "properties": [],
        "GUID": "26ea7fe2-a799-11ec-9997-157f1432aaf9"
    },
    "sources": [],
    "decorativeSymbols": [],
    "dbVersion": "v4.4",
    "dbVendor": "MongoDB",
    "appTarget": "MONGODB",
    "creationTS": "2022-03-19T15:27:56.637Z",
    "GUID": "26ea7fe0-a799-11ec-9997-157f1432aaf9",
    "isLineageEnabled": false,
    "lastModifTS": "2022-03-23T13:46:31.932Z",
    "persistenceSchemaVersion": "5",
    "isCreatedByPlugin": true,
    "pluginInformation": {
        "pluginEngineVersion": "1.0.0"
    },
    "applicationInformation": {
        "version": "5.4.9"
    },
    "hackoladeMeta": {},
    "settings": {
        "centralPane": {
            "dbLevel": {
                "erd": [
                    {
                        "GUID": "9f1d99d0-a7b1-11ec-b8be-0f7e6033a1b6",
                        "x": 131,
                        "y": 224,
                        "width": 240,
                        "height": 100,
                        "color": {}
                    }
                ],
                "buckets": [
                    {
                        "x": 91,
                        "y": 184,
                        "GUID": "2855a8a0-a799-11ec-9997-157f1432aaf9"
                    }
                ],
                "collapsedNodes": [],
                "activeRelationship": "",
                "activeRelationshipFields": {
                    "childField": [],
                    "parentField": []
                },
                "selectedCollections": [],
                "displayColorPicker": false,
                "graphView": {
                    "erd": [],
                    "buckets": [],
                    "decorativeSymbols": [],
                    "forceLayout": true,
                    "defaultLinkLength": 300
                },
                "diagramViews": [],
                "decorativeSymbols": [],
                "nestedCollectionsLayout": "horizontal",
                "options": []
            },
            "collectionLevel": {},
            "changed": false
        },
        "dtDiagram": {
            "collapsedNodes": [],
            "shouldDistributeCollections": false
        }
    }
}
